JSONSchemaLibrary/__init__.py
robot_jsonschemalibrary-0.1.1.dist-info/METADATA
robot_jsonschemalibrary-0.1.1.dist-info/WHEEL
robot_jsonschemalibrary-0.1.1.dist-info/top_level.txt
robot_jsonschemalibrary-0.1.1.dist-info/RECORD
