Metadata-Version: 2.1
Name: robot-jsonschemalibrary
Version: 0.1.1
Summary: A Robot Framework library for JSON Schema validation.
Home-page: https://github.com/hypc/robot-jsonschemalibrary
Author: hypc
Author-email: h_yp00@163.com
License: MIT
Keywords: robotframework json jsonschema
Platform: UNKNOWN
Classifier: Development Status :: 5 - Production/Stable
Classifier: Framework :: Robot Framework
Classifier: License :: OSI Approved :: MIT License
Classifier: Programming Language :: Python :: 3
Classifier: Programming Language :: Python :: 3.2
Classifier: Programming Language :: Python :: 3.3
Classifier: Programming Language :: Python :: 3.4
Classifier: Programming Language :: Python :: 3.5
Classifier: Programming Language :: Python :: 3.6
Requires-Python: >=3
Requires-Dist: robotframework
Requires-Dist: jsonschema
